setup.py
ogmsservice/__init__.py
ogmsservice/base.py
ogmsservice/data.py
ogmsservice/geodatacontainerserver.py
ogmsservice/geodataexserver.py
ogmsservice/geotaskserver.py
ogmsservice/modelserivce.py
ogmsservice/modelserviceinstance.py
ogmsservice/modelservicerecord.py
ogmsservice/ogmsservice.py
ogmsservice/runninglog.py
ogmsservice/server.py
ogmsservice/test.py
ogmsservice/test_task.py
ogmsservice/utils.py
ogmsservice.egg-info/PKG-INFO
ogmsservice.egg-info/SOURCES.txt
ogmsservice.egg-info/dependency_links.txt
ogmsservice.egg-info/requires.txt
ogmsservice.egg-info/top_level.txt
ogmsservice.egg-info/zip-safe